ai_service_wrapper/__init__.py
ai_service_wrapper/fastapi_app.py
ai_service_wrapper/flask_app.py
ai_service_wrapper/apikey/__init__.py
ai_service_wrapper/apikey/apikey_tracking.py
ai_service_wrapper/apikey/verify.py
ai_service_wrapper/apisignature/__init__.py
ai_service_wrapper/apisignature/decorators.py
ai_service_wrapper/apisignature/endecrypt.py
ai_service_wrapper/apisignature/sign.py
ai_service_wrapper/apisignature/verify.py
ai_service_wrapper/utils/__init__.py
ai_service_wrapper/utils/logger.py
ai_service_wrapper/utils/fastapi/__init__.py
ai_service_wrapper/utils/fastapi/exceptions.py
ai_service_wrapper/utils/fastapi/http_scheme.py
ai_service_wrapper/utils/fastapi/middlewares.py
ai_service_wrapper/utils/fastapi/settings.py
ai_service_wrapper/utils/flask/__init__.py
ai_service_wrapper/utils/flask/error_handler.py
ai_service_wrapper/utils/flask/http_scheme.py
ai_service_wrapper/utils/flask/setup_prometheus_hook.py
ai_service_wrapper/utils/prometheus/__init__.py
ai_service_wrapper/utils/prometheus/metrics.py
tests/__init__.py
tests/test_apiSignature.py
ai_service_wrapper-0.0.8.dist-info/METADATA
ai_service_wrapper-0.0.8.dist-info/WHEEL
ai_service_wrapper-0.0.8.dist-info/top_level.txt
ai_service_wrapper-0.0.8.dist-info/RECORD
