Metadata-Version: 2.1
Name: ai-service-wrapper
Version: 0.0.8
Summary: update lifetime for api signature
Author: Engreed68
Author-email: trungpn@apero.com
License: MIT
Classifier: Intended Audience :: Developers
Classifier: License :: OSI Approved :: MIT License
Classifier: Programming Language :: Python
Classifier: Programming Language :: Python :: 3
Classifier: Programming Language :: Python :: 3.6
Classifier: Programming Language :: Python :: 3.7
Classifier: Programming Language :: Python :: 3.8
Classifier: Programming Language :: Python :: 3.9
Classifier: Programming Language :: Python :: 3.11
Classifier: Operating System :: OS Independent
Requires-Dist: cryptography ==41.0.3
Requires-Dist: Flask ==2.3.3
Requires-Dist: prometheus-client ==0.17.1
Requires-Dist: pytest ==7.4.0
Requires-Dist: python-dotenv ==1.0.0
Requires-Dist: requests ==2.31.0
Requires-Dist: fastapi
Requires-Dist: uvicorn[standard]
Requires-Dist: prometheus-fastapi-instrumentator
